README.rst
setup.py
pymo/__init__.py
pymo/_version.py
pymo/errors.py
pymo/monitor.py
pymo/monitoring.py
pymo/pymongo2.py
pymo/pymongo3.py
pymo/selectors.py
pymo.egg-info/PKG-INFO
pymo.egg-info/SOURCES.txt
pymo.egg-info/dependency_links.txt
pymo.egg-info/requires.txt
pymo.egg-info/top_level.txt
pymo/tests/__init__.py