Metadata-Version: 1.1
Name: pymo
Version: 0.2.0
Summary: MongoClient instrumentation and factory
Home-page: https://github.com/mlab/pymo
Author: Greg Banks
Author-email: UNKNOWN
License: MIT
Keywords: pymongo mongodb driver
Platform: UNKNOWN
Classifier: Development Status :: 5 - Production/Stable
Classifier: Intended Audience :: Developers
Classifier: Topic :: Software Development :: Libraries :: Python Modules
Classifier: License :: OSI Approved :: MIT License
Classifier: Programming Language :: Python :: 2.7
